src/__init__.py
src/config.py
src/getFromApi.py
src/insert.py
src/run.py
profile_linkedin_graphql_imp_local-0.0.1.dist-info/METADATA
profile_linkedin_graphql_imp_local-0.0.1.dist-info/WHEEL
profile_linkedin_graphql_imp_local-0.0.1.dist-info/top_level.txt
profile_linkedin_graphql_imp_local-0.0.1.dist-info/RECORD
