Metadata-Version: 2.1
Name: profile-linkedin-graphql-imp-local
Version: 0.0.1
Summary: PyPI Package for Circles <project-name> Local/Remote Python
Home-page: https://github.com/circles
Author: Circles
Author-email: info@circles.life
Classifier: Programming Language :: Python :: 3
Classifier: License :: Other/Proprietary License
Classifier: Operating System :: OS Independent
